{
  "week1": {
    "day1": [
      {
        "name": "front squat",
        "type": [
          "squat",
          "accessory"
        ],
        "weight": [
          0.3,
          0.4,
          0.5,
          0.5,
          0.5
        ],
        "reps": [
          4,
          4,
          4,
          4,
          4
        ]
      },
      {
        "name": "bench",
        "type": [
          "bench",
          "main"
        ],
        "weight": [
          0.5,
          0.6,
          0.7,
          0.75,
          0.75,
          0.75,
          0.75
        ],
        "reps": [
          5,
          4,
          3,
          2,
          2,
          2,
          2
        ]
      },
      {
        "name": "squat",
        "type": [
          "squat",
          "main"
        ],
        "weight": [
          0.55,
          0.65,
          0.75,
          0.75,
          0.75,
          0.75
        ],
        "reps": [
          3,
          3,
          2,
          2,
          2,
          2
        ]
      }
    ]
  }
}